[{"type":"complex-table","grid":[[{"content":"क.सं.","align":"center","header":true},{"content":"समय","align":"center","header":true},{"content":"स्थान","align":"center","header":true},{"content":"स्रोतहरू","align":"center","header":true},{"content":"घटना","align":"center","header":true}],[{"content":"१.","align":"center"},{"content":"०७:५५ -","align":"center"},{"content":"संसद भवन दक्षिण गेट, बानेश्वर","align":"center"},{"content":"CCTV: Civil Hospital PTZ, Commerce Campus Minbhawan","align":"center"},{"content":"आन्दोलनकारीहरु बिहानदेखि नै संसद भवनको दक्षिण गेट अगाडी जम्मा भए २३ गते भाचेको फलामे बारहरू समेत","align":"left"}],[{"content":"","align":"center"},{"content":"०८:२४","align":"center"},{"content":"","align":"center"},{"content":"","align":"center"},{"content":"मुख्य सडक खण्डमा तेर्साई बाटो बन्द गर्न खोजेको देखिन्छ।","align":"left"}],[{"content":"२.","align":"center"},{"content":"०९:१८","align":"center"},{"content":"मिनभवन क्याम्पस गेट जाने मुख्य सडक खण्ड","align":"center"},{"content":"CCTV: Nepal Commerce Campus Minbhawan","align":"center"},{"content":"मिनभवनको मुख्य सडक खण्डमा आन्दोलनकारीहरू जम्मा भई आन्दोलन शुरु गरेको देखिन्छ।","align":"left"}],[{"content":"३.","align":"center"},{"content":"११:३१ - ११:५५","align":"center"},{"content":"वबरमहल देखि बिजुलीबजार स्थित कृष्ण टावर","align":"center"},{"content":"CCTV: Krishna Tower PTZ","align":"center"},{"content":"सर्वप्रथम आन्दोलनकारी बिजुलीबजार नजिक रहेको कृष्ण टावर अगाडी जम्मा भएको र वबरमहलबाट आएको आन्दोलनकारीसँग भेटि बानेश्वर तर्फ अगि बढेको देखिन्छ।","align":"left"}],[{"content":"४.","align":"center"},{"content":"११:५८","align":"center"},{"content":"बानेश्वर चोक","align":"center"},{"content":"CCTV: Baneshwor Chowk PTZ","align":"center"},{"content":"बानेश्वर चोकमा आन्दोलनकारीहरुले आगजनी गरेको पश्चात नेपाल प्रहरीले लिएको डिउटिको फर्मेशन छोड्ि ठ्याक भएको देखिन्छ।","align":"left"}],[{"content":"५.","align":"center"},{"content":"१२:०० - १२:०१","align":"center"},{"content":"च्यासल","align":"center"},{"content":"Onlinekhabar news & onlinekhabar Drone Footage","align":"center"},{"content":"च्यासलस्थित एमालेको केन्द्रियकार्यालयमा आगजनी सुरु भएको उल्लेख गरेको छ भने अनलाइनखबरबाट प्राप्त ड्रोन फुटेजमा १२:०१ मा आगजनी भईरहेको र त्यस क्षेत्र वरपर रहेका अन्य भवन, व्यापारिक प्रतिष्ठानहरुमा समेत आगलागी भईरहेको देखिन्छ।","align":"left"}],[{"content":"६.","align":"center"},{"content":"१२:११ - १३:०१","align":"center"},{"content":"बानेश्वर चोक","align":"center"},{"content":"CCTV: Baneshwor Chowk PTZ र Everest Hotel, OnlineKhabar, OnlineKhabar बाट प्राप्त Drone Footage","align":"center"},{"content":"बानेश्वर चोकमा रहेको ट्राफिक प्रहरीको आईल्याण्डमा आन्दोलनकारीहरुले आगजनी गरेको देखिन्छ, अर्को भीड बानेश्वर चोक तर्फ नयाँजाती गर्दै अगाडि बढेको १३:०१ मा अनलाइनखबरबाट प्राप्त ड्रोन फुटेज अनुसार आन्दोलनकारीहरु नयाँ बानेश्वर चोक देखि पश्चिम गेट तर्फ भेला भइरहेको देखिन्छ।","align":"left"}],[{"content":"७.","align":"center"},{"content":"१३:०८ - १३:१४","align":"center"},{"content":"यातायात कार्यालय बानेश्वर","align":"center"},{"content":"Onlinekhabar news","align":"center"},{"content":"संसद भवन नजिक रहेको यातायात कार्यालयमा आन्दोलनकारीहरुले आगजनी गरेका छन् भने अनलाइनखबरबाट प्राप्त ड्रोन फुटेज उसै समयमा यातायात कार्यालयमा आगलागी भईरहेको र संसद भवन परिसरको मुख्य गेटमा सुरक्षाकर्मी फर्मेशनमा रहेको परिसर भित्र आन्दोलनकारी नदेखिएको अवस्था रहेको देखिन्छ।","align":"left"}],[{"content":"८.","align":"center"},{"content":"१३:१४ - ०२:५६","align":"center"},{"content":"बानेश्वर चोक लगायत संसद भवन वरीपरी","align":"center"},{"content":"Onlinekhabar news र Onlinekhabar प्राप्त Drone","align":"center"},{"content":"बानेश्वरमा Youth Against Corruption को पम्फलेट सहितको ठूलो भीड बानेश्वर चोकबाट अगाडी बढि रहेको देखिन्छ भने अनलाईन खबरबाट प्राप्त ड्रोन फुटेजमा ०२:५० मा संसद भवनमा आगो लागेको सुरु गर्न सकेको देखिन्छ भने अनलाईन खबरबाट प्राप्त ड्रोन फुटेजमा ०२:५६ मा संसद भवनमा आगो लागेको देखिन्छ।","align":"left"}]]},{"type":"list","list-type":"disc","content":[{"content":"Civil Hospital PTZ ¥ Nepal Commerce Campus MinBhawan बिहान ०७:५८ देखि नै आन्दोलनकारी बानेश्वर संसद भनव मेन गेट अगाडी जम्मा भई ०८:२४ मा अघिल्लो दिन बाचेको फलामे बारहरू समेत मेन गेट अगाडीको बाटोमा तेर्साई गाडीहरू बन्द गर्न खोजेको |"},{"content":"Nepal Commerce Campus MinBhawan 0९:१८ मा मिनभवन क्याम्पस अगाडी आन्दोलनकारीहरू जम्मा भइ आन्दोलन शुरु गरेको ।"},{"content":"Krishna Tower PTZ ११:३१ मिनेटमा सर्वप्रथम आन्दोलनकारीहरु बिजुलीबजार नजिकै रहेको Krishna Tower अगाडी जम्मा हुन सुरु गरी ११: ५५ मा बबरमहल तर्फबाट आएको आन्दोलनकारीहरु सँग मिसिइ वानेश्वर तर्फ अघि वढेको |"},{"content":"Baneshwor Chowk PTZ पहिलो पल्ट ११:५८ मा बानेश्वर चोकमा आन्दोलनकारीहरूले आगजानी गरेको पश्चात नेपाल प्रहरीले लिएको डिउटिको फर्मेशन छोडि व्याक भएको ।"},{"content":"www.onlinekhabar.com का अनुसार १२:०० मा च्यासलस्थित एमालेको केन्द्रियकार्यालयमा आगजनी सुरु भएको उल्लेख गरेको छु भने अनलाइनखबरबाट प्राप्त ड्रोन फुटेजमा १२:०१ मा आगजनी भईरहेको र त्यस क्षेत्र वरपर रहेका अन्य भवन, व्यापारिक प्रतिष्ठानहरुमा समेत आगलागी भईरहेको देखिन्छ |"},{"content":"Baneshwor Chowk PTZ र Everest Hotel | आन्दोलनकारीहरूले १२:११ बजे बानेश्वर चोकमा रहेको ट्राफिक प्रहरीको आईल्याण्डमा आन्दोलनकारहरुले आगजानी गरेको देखिन्छ र सोही घटना www. onlinekhabar.com T अनुसार १२:१४ मा ट्राफीख बिटमा आगजनी गरेको उल्लेख गरेको छ। १२:४५ मा फेरी अर्को भीड बानेश्वर चोक तर्फ नाराबाजी गर्दै अगाडी वढेको १३:०१ मा अनलाइनखवरवाट प्राप्त ड्रोन फुटेज अनुसार आन्दोलनकारीहरु नयाँ बानेश्वर चोक देखि पश्चिम गेट तर्फ भेला भइरहेको देखिन्छ।"},{"content":"www.onlinekhabar.com ले उल्लेख गरे अनुसार १३:०८ मा संसद भवन नजिकै रहेको यातायात कार्यालयमा आन्दोलनकारीहरुले आगजनी गरेका छन् भने अनलाइनखवरबाट प्राप्त ड्रोन फुटेज सो समयमा यातायात कार्यालयमा आगलागी भईरहेको र संसद भवन परिसरको मुख्य गेटमा सुरक्षाकर्मी फर्मेशनमा रहेको परिसर भित्र आन्दोलनकारी नदेखिएको अवस्था रहेको देखिन्छ।"},{"content":"अनलाईन खबरबाट प्राप्त ड्रोन फुटेजमा १३:१४ मा वानेश्वरमा Youth Against Corruption 'को पम्पेलट सहितको ठूलो भीड वानेश्वर चोकबाट अगाडी बढि रहेको देखिन्छ।"},{"content":"www.onlinckhabar.com ले उल्लेख गरे अनुसार ०२:५० मा संसद भवनमा आगजनी शुरु गरि सकेको देखिन्छ भने अनलाईन खबरबाट प्राप्त ड्रोन फुटेजमा ०२:५६ मा संसद भवनमा आगो लागेको देखिन्छ |"}]},{"type":"p","content":"(*Source: छभवकाडता/उपत्यका प्रहरी कार्यालय सिसिटिभि फुटेज/CCTV Valley Police/2nd Time Footage/Export 11-3-2025 1-02-38 PM/Media Player Format/Civil Hospital PTZ, Nepal Commerce Campus Minbhawan, Export 11-3-2025 1-04-23 PM/Media Player Format/Baneshwor Chowk PTZ, Everest Hotal PTZ, Krishana Tower PTZ https://www.onlinekhabar.com/interactive/interactive-protest-timeline.html )"},{"type":"p","content":"संहदरवार क्षेर"},{"type":"complex-table","grid":[[{"content":"क.सं.","align":"center","header":true},{"content":"समय","align":"center","header":true},{"content":"स्थान","align":"center","header":true},{"content":"स्रोतहरू","align":"center","header":true},{"content":"घटना","align":"center","header":true}],[{"content":"१.","align":"center"},{"content":"१३:०२ - १३:३०","align":"center"},{"content":"भद्रकाली देखि सिंहदरबार पश्चिम गेट सम्म","align":"center"},{"content":"CCTV: Bhadrakali PTZ, Singha Durbar Paschim Gate","align":"center"},{"content":"आन्दोलनकारीहरू सिंहदरबारको पश्चिम गेट तर्फ अगाडी बढिरहेको तथा नेपाल प्रहरीको वाटर क्यानन तथा सुरक्षाकर्मीहरू समेत आफ्नो फर्मेशनमा डिउटि लिई रहेको देखिन्छ, नेपाल प्रहरीको Water गएको तथा आन्दोलनकारीहरू मध्ये आधि जती आन्दोलनकारीहरू प्रदर्शनी मार्ग तर्फ मोडिङ उपत्यका ट्राफिक प्रहरी अगाडी सम्म राखिएका डिबाइडरहरू तोडफोड गर्न सुरु गरेको देखिन्छ, प्रदर्शनी मार्ग तिरबाट ठूलो संख्यामा भीड हातमा लठ्ठि, फलाम बासहरू लिइ सिंहदरबार गेटमा जम्मा भए प्रहरीको ब्यारेक गेट समेत तोडफोड गरी मुख्य बाटोमा टायरमा आगजनी गरेको, सुरक्षाकर्मीहरू मेन गेटबाट सानो गेट तर्फ सरेको साथै आन्दोलनकारी पश्चिम गेटमा चढि सकेको, सुरक्षाकर्मीहरू पश्चिम गेटबाट सानो गेटमा सरे पश्चात आन्दोलनकारीहरू पश्चिम गेट भित्र नै छिरि सकेको तथा बाहिरको डिउटि सम्पूर्ण पश्चिम गेट भित्र छिरेको देखिन्छ।","align":"left"}],[{"content":"२.","align":"center"},{"content":"१३:४० - १३:४९","align":"center"},{"content":"सिंहदरबार पश्चिम गेट अगाडी","align":"center"},{"content":"CCTV: Singha Durbar Paschim Gate, Inside VIP Gate","align":"center"},{"content":"आन्दोलनकारी सिंहदरबार पश्चिम गेट भित्र छिरी सकेको देखिन्छ भने अनलाइन खबरबाट प्राप्त ड्रोन फुटेजमा १३:४९ मा आन्दोलनकारीको भीड सिंहदरबारको पश्चिम गेट अगाडी तिर भाग्दै गरेको देखिन्छ, अनलाइन खबरबाट प्राप्त ड्रोन फुटेजमा १३:४९ मा आन्दोलनकारी मेनगेट गेटमा चढ्न सुरु गरेको देखिन्छ।","align":"left"}],[{"content":"३.","align":"center"},{"content":"१५:०३ - १५:१५","align":"center"},{"content":"सिंहदरबार पश्चिम गेट अगाडी","align":"center"},{"content":"CCTV: Old Home Turning, Onlinekhabar Drone Footage","align":"center"},{"content":"पहिलो पल्ट आन्दोलनकारीहरू प्रधानमन्त्री परिसर अगाडी पुगेको देखिन्छ, ठूलो आगो दन्किन सुरु गरेको देखिन्छ तथा अनलाईन खबरबाट प्राप्त ड्रोन फुटेज अनुसार १५:१३ मा सिंहदरबार परिसरमा ठूलो मात्रामा धुवा उडेको देखिन्छ।","align":"left"}],[{"content":"४.","align":"center"},{"content":"१४:५५","align":"center"},{"content":"सिंहदरबार दक्षिण गेट","align":"center"},{"content":"CCTV: Singha Durbar Dakshin Gate","align":"center"},{"content":"आन्दोलनकारीहरू दक्षिण गेटमा तोडफोड तथा आगजनी सुरु गरेको देखिन्छ।","align":"left"}],[{"content":"५.","align":"center"},{"content":"१५:०७","align":"center"},{"content":"प्रधानमन्त्री कार्यालयको पार्किङ","align":"center"},{"content":"CCTV: PM Parking","align":"center"},{"content":"आन्दोलनकारीहरुले प्रधानमन्त्री कार्यालयको पार्किङमा रहेको मोटरसाइकल तथा गाडीमा तोडफोड तथा आगजनी गरेको।","align":"left"}],[{"content":"६.","align":"center"},{"content":"१५:०९","align":"center"},{"content":"सिंहदरबार भित्रको मुख्य पार्किङ","align":"center"},{"content":"CCTV: Main parking","align":"center"},{"content":"आन्दोलनकारीहरुले पार्किङमा रहेको मोटरसाइकल तथा गाडीमा तोडफोड तथा आगजनी गरेको।","align":"left"}],[{"content":"७.","align":"center"},{"content":"१५:१८","align":"center"},{"content":"शिक्षा मन्त्रालय तथा गृह पार्किङ","align":"center"},{"content":"CCTV: Sikshya Parking, Griha Parking","align":"center"},{"content":"आन्दोलनकारीहरुको समूहले आगजनी तथा तोडफोड सुरु गरेको देखिन्छ।","align":"left"}]]},{"type":"list","list-type":"disc","content":[{"content":"Bhadrakali PTZ भद्रकालीबाट १३:०२ मिनेटमा आन्दोलनकारीहरू सिंहदरवारको पश्चिम गेट तर्फ अगाडी बढिरहेको तथा नेपाल प्रहरीको वाटर क्यानन तथा सुरक्षाकर्मीहरू समेत आफ्नो फर्मेशनमा डिउटि लिई रहेको देखिन्छ।"},{"content":"Singha Durbar Paschim Gate PTZ Wfeell पल्ट १३:०५ मिनेटमा गेट अगाडी पुगे पश्चात लगत्तै नेपाल प्रहरीको Water गएको तथा आन्दोलनकारीहरू मध्ये आधि जती आन्दोलनकारीहरू प्रदर्शनी मार्ग तर्फ मोडिइ उपत्यका ट्राफिक प्रहरी अगाडी सम्म राखिएका डिभाइडहरू तोडफोड गर्न सुरु गरेको देखिन्छ |"},{"content":"Singha Durbar Paschim Gate PTZ १३:१२ प्रर्दशनी मार्ग तिरवाट ठूलो संख्यामा भीड हातमा लष्टि, फलाम बासहरू लिइ सिंहदरवार पश्चिम गेटमा जम्मा भए प्रहरीको ब्यारेक गटे समेत तोडफोड गरी मुख्य बाटोमा टायरमा आगजनी गरेको |"},{"content":"Singha Durbar Paschim Gate PTZ १३:२६ मिनेटमा सुरक्षाकर्मीहरू मेन गेटबाट सानो गटे तर्फ सरेको साथै आन्दोलनकारी पश्चिम गेटमा चढि सकेको तथा १३:३० मिनेटमा सुरक्षाकर्मीहरु पश्चिम गेटबाट सानो गेटमा सरे पश्चात आन्दोलनकारीहरू पश्चिम गेट भित्र नै छिरि सकेको तथा बाहिरको डिउटि सम्पूर्ण पश्चिम गेट भित्र छिरेको देखिन्छु ।"},{"content":"Inside of VIP Gate १३:४० बजे पहिलो पल्ट आन्दोलनकारी सिंहदरवार पश्चिम गेट भित्र छिरी सेकेको देखिन्छ भने अनलाइन खबरबाट प्राप्त ड्रोन फुटेजमा १३:४९ मा आन्दोलनकारीको भीड सिंहदरवारको पश्चिम गेट अगाडी तिर भाग्दै गरेको देखिन्छ।"},{"content":"अनलाइन खबरबाट प्राप्त ड्रोन फुटेजमा १३:४९ मा आन्दोलनकारीहरू पश्चिम गेटमा चढ्न शुरु गरेको देखिन्छ।"}]},{"type":"p","content":"Old Home Affair Turning १५:०३ मा पहिलो पल्ट आन्दोलनकारीहरू प्रधानमन्त्री परिसर अगाडी पुगेको देखिन्छ भने १५:१५ मा ठूलो आगो दन्किन शुरु गरेको देखिन्छ तथा अनलाईन खबरबाट प्राप्त ड्रोन फुटेज अनुसार १५:१३ मा सिंहदरवार परिसरमा ठूलो मात्रामा धुवा उडेको देखिन्छु |"},{"type":"list","list-type":"disc","content":[{"content":"Singha Durbar Dakshin Gate १४:५५ आन्दोलनकारीहरू दक्षिण गेटमा तोडफोड तथा आगजनी शुरु गरेको देखिन्छ।"},{"content":"Main Parking १५:०९ मा आन्दोलनकारीहरूले पार्किङमा रहेको मोटरसाइकल तथा गाडीमा तोडफोड तथा आगजनी गरको ।"},{"content":"PM Parking १५:०७ मा आन्दोलनकारीहरूले पार्किङमा रहेको गाडीहरू आगजनी तथा तोडफोड गरेको देखिन्छ।"},{"content":"Sikshya Parking र Griha Parking १५:१८ मा आन्दोलनकारीहरूको समूहले आगजनी तथा तोडफोड शुरु गरेको देखिन्छ।"}]},{"type":"p","content":"(*Source: HardDisk 1/सिंहदरवार/(( W/ NVRI/PM Parking, D06,020, D22,023,D32, https://www.onlinekhabar.com/interactive/interactive-protest-timeline.html )"},{"type":"h4","content":"घटनाको विश्लेषण"},{"type":"p","content":"२०८२ भाद्र २३ गते काठमाडौंमा भ्रष्टाचारविरुद्ध युवा विद्यार्थीहरूको माइतीघर मण्डलाबाट सुरु भई नयाँ बानेघर चोक हुँदै संसद भवनसम्म फैलिएको थियो। विभिन्न सीसीटीभी फुटेज, युट्युब च्यानलहरू र अनलाइन मिडियाका आधारमा यो घटनाको क्रमिक विवरण यस प्रकार छुः"},{"type":"h4","content":"प्रदर्शनको सुरुवात: माइतीघरमा भेला"},{"type":"p","content":"बिहान ८:२३ बाटै विद्यार्थीहरू माइतीघर आसपास प्लेकार्डसहित भेला हुन थालेका थिए। बिहान ९:१४ सम्म थोरै संख्यामा प्रदर्शनकारीहरू राष्ट्रिय झण्डासहित माइतीघर मण्डला क्षेत्रमा जम्मा भएका देखिन्छन्। उनीहरू भरष्टाचारविरुद्ध नारा लगाउँदै विद्यार्थी पोसाकमा थिए।"},{"type":"p","content":"बिहान १०:०० सम्म माइतीघर क्षेत्रमा प्रदर्शनकारीको भीड बढ्दै गयो। १०:२५ सम्म मण्डलाको दक्षिण सडक लेनमा प्रदर्शनकारीहरू थिए भने अन्य लेनमा सवारी साधनहरू सामान्य रूपमा चलिरहेका थिए। १०:२७ बाट केही प्रदर्शनकारीहरू विजुली बजारतर्फ लागेका देखिन्छन्। ईओएन युट्युब च्यानलका अनुसार १०:५२ मा नेपाल टेलिकमको कार्यालय नजिकको पोलमा रहेको तत्कालीन प्रधानमन्त्री केपी ओलीको तस्विर देखेर प्रदर्शनकारीहरू आक्रोशित भई च्यातेक थिए, जुन बिजुली बजार पीटीजेड सीसीटीभीमा १०:५२ मा कैद भएको छ।"},{"type":"h4","content":"निषेधित क्षेत्रतर्फ अघि बढ्दै प्रदर्शन"},{"type":"p","content":"बिजुली बजार पीटीजेड र एभरेस्ट होटल पीटीजेड सीसीटीभीका अनुसार १०:५८ मा विजुली बजार पुल हुँदै प्रदर्शनकारीहरूको पहिलो समूह निषेधित क्षेत्रतर्फ रहेको व्यारिकेटतर्फ बढेका थिए। ११:०० मा उनीहरू व्यारिकेटमा सुरक्षाकर्मीसँग आमनेसामने भएका थिए।"},{"type":"p","content":"एभरेस्ट होटल पीटीजेड सीसीटीभीमा ११:४० मा एभरेस्ट अस्पतालतर्फबाट केही प्रदर्शनकारीहरू प्रहरीको व्यारिकेटको पछाडितर्फ पुगेका देखिन्छन्, जसलाई सशस्त्र प्रहरीको टोलीले हटाएको थियो | ११:४७ मा पुनः सोही दिशाबाट अघिल्लो पटकभन्दा धेरै संख्यामा प्रदर्शनकारीहरू आएका थिए। एउटा समूहले प्रहरीको व्यारिकेट तोड्न प्रयास गरेको थियो भने अर्को समूह नयाँ बानेश्वर चोकतर्फ अघि बढेको थियो। व्यारिकेटतर्फ लागेका प्रदर्शनकारीहरूले व्यारिकेट तोडी ठूलो समूह चोकतर्फ लागेका थिए।"},{"type":"p","content":"११:४९ मा बाइकसहितका प्रदर्शनकारीहरू नयाँ बानेश्वर चोकतर्फ बढेका थिए। ११:५४ मा प्रहरीले भीडलाई रोक्न आफ्नो फर्मेसनमा रहन प्रयास गरेको थियो। एउटा सानो समूह नयाँ वानेश्वर चोकमा पुगेको थियो, जहाँ सार्वजनिक तथा निजी सवारी साधनहरू सुचारु थिए। ११:५५ मा भीडलाई तितरबितर पार्न प्रहरीले वाटर क्यानन प्रयोग गरेको थियो। तर, भीडले प्रहरीमाथि ढुंगा प्रहार गरेपछि प्रहरीले वाटर क्यानन र अशुग्यास प्रयोग गर्दै बानेश्वर चोकतर्फ पछि हटेको थियो । भीडको मुख्य जमात संसद भवनतर्फ अघि बढेको थियो |"},{"type":"p","content":"बानेघर चोक २ सीसीटीभीमा ११:५५ मा सवारी साधनहरू सुचारु रहँदै गर्दा प्रहरी e प्रहार गर्दै संसद भवनतर्फ पछि हटिरहेको देखिन्छ भने प्रदर्शनकारीहरू  'Youth Against Corruption” लेखिएको ब्यानरसहित संसद भवनतर्फ बढेका थिए।"},{"type":"h4","content":"संसद भवन गेटमा पुग्दै प्रदर्शनकारीहरू"},{"type":"p","content":"सिभिल अस्पताल पीटीजेड सीसीटीभीमा ११:५१ मा बाइकसवारसहितको पहिलो समूह संसद भवन गेट अगाडी पुगेको देखिन्छु भने संसद भवनको मेन गेटमा रहेको क्यामेराका अनुसार ११:४६ मा सो समूह पुगेको थियो। अनलाइनखबर डटकमका अनुसार ११:४९ मा २० जना जतिको समूह पुगेको उल्लेख छ।"},{"type":"p","content":"बीआईसीसी अगाडी रहेको सीसीटीभीमा ११:५४ मा प्रहरीद्वारा अश्वुग्यास प्रयोग गरी भीडलाई तितरबितर बनाएको थियो। ११:५७ मा वाटर क्यानन पछ्याउँदै प्रदर्शनकारीहरू मेन गेट अगाडी पुगेका थिए। १२:०१ मा सुरुमा दुई जना प्रदर्शनकारीहरू गेटमाथि चढेका देखिन्छन् भने सिभिल अस्पताल नजिक रहेको सीसीटीभीमा १२:०५ मा पर्खाल चढी गेटमाथि चढेको देखिन्छ। नयाँ बानेश्वर चोकबाट ठूलो संख्यामा आएको भीड संसद भवन गेट नजिक जम्मा भएपछि सडकपेटीमा रहेको रेलिङ तोडेर त्यही रेलिङको सहारामा प्रदर्शनकारीहरू गेटमाथि चढेका थिए।"},{"type":"p","content":"१२:०५ मा बीआईसीसी पीटीजेड सीसीटीभीमा ठूलो मात्रामा प्रदर्शनकारीहरू बीआईसीसी मेन गेट अगाडी जम्मा भइसकेका थिए। बीआईसीसी गेटमाथि रहेका प्रदर्शनकारीहरूलाई लक्षित गरी अश्नुग्यास प्रहार भएको थियो भने प्रदर्शनकारीहरूले अश्ुग्यास सेल प्रहरीतर्फ नै प्रहार गरेका थिए। सोही घटना सिभिल अस्पताल पीटीजेडमा १२:१० मा देखिएको छ। अनलाइनखबर र ईओएन युट्युब च्यानलबाट समेत यस सम्बन्धी घटनाक्रम उल्लेख गरिएको छ।"},{"type":"h4","content":"घाइतेहरूको उपचार र कर्फ्यू आदेश"},{"type":"p","content":"सिभिल अस्पताल इमर्जेन्सी सीसीटीभी फुटेजमा १२:०७ मा आँखाको तल्लो भागमा चोट लागेको विद्यार्थी पोसाकमा रहेको पहिलो घाइते इमर्जेन्सी कक्षमा प्रवेश गरेको देखिन्छ। १२:१७ बाट घाइतेहरू उपचारार्थ आउने संख्यामा वृद्धि भएको थियो भने १२:४१ मा शरीरका विभिन्न अंगहरूबाट रगत आएको देखिने घाइते प्रदर्शनकारीहरू इमर्जेन्सी कक्षमा आउने क्रम सुरु भएको थियो ।"},{"type":"p","content":"जिल्ला प्रशासन कार्यालय, काठमाडौंले १२:३० बाट लागु हुने गरी कर्फ्यू आदेश जारी गरेको थियो। बीआईसीसी पीटीजेड सीसीटीभीमा १२:२९ मा बाइकसवारको आगमन देखिन्छ भने एक जना मेट गेटतर्फबाट १२:३३ मा पेट समात्दै आएको (सम्भावित गोली प्रहारबाट) र सिभिल अस्पतालको इमर्जेन्सी क्यामेराबाट १२:५४ मा पेटबाट रगत बगिरहेको अवस्थामा उपचारार्थ आएको देखिन्छ। बीआईसीसी पीटीजेड सीसीटीभीमा १२:३४ मा वीआईसीसीको गेट नजिक आगजनी भएको थियो भने अनलाइनखबरको समाचार अनुसार १२:३७ मा प्रदर्शनकारी ताक्दै गोली प्रहार भएको थियो। नेपाल कमर्स क्याम्पसको सीसीटीभी अनुसार १२:४१ मा दुई एम्बुलेन्स सिभिल अस्पतालतर्फ गएका थिए।"},{"type":"p","content":"करिब १३:१५ बाट संसद भवनको पश्चिम गेटमा प्रदर्शनकारीहरूले सुरक्षाकर्मीलाई लक्षित गरी ढुंगामुडा गरेका थिए भने गेटसमेत तोडफोड गर्ने प्रयास गरेका थिए। प्रहरीले प्रदर्शनकारीमाथि AT प्रहार गरेको थियो।"},{"type":"p","content":"बीआईसीसी पीटीजेडमा १२:३५ मा प्रहरीद्वारा मेन गेट वरपर जम्मा भएका प्रदर्शनकारीहरूलाई लक्षित गरी टियर ग्यास प्रहार भएको थियो। १२:४० मा संसद भवन परिसरबाट गेट भित्रबाट पानीको फोहोरा प्रहार गरिएको थियो। १२:५५ मा गोली प्रहारबाट घाइतेलाई उद्धार गर्दै गरेको देखिन्छ। १२:५४ पछि गोली प्रहारबाट घाइते प्रदर्शनकारीको संख्यामा व्यापक वृद्धि भएको थियो । १३:०१ मा प्रदर्शनकारीद्वारा प्रहरी लक्षित गरी मोलोटोभ प्रहार भएको थियो भने १३:०५ मा प्रहरीद्वारा मेन गेट अगाडी प्रदर्शनकारीको टाउकोमा गोली प्रहार गरेको देखिन्छ, जुन घटना युट्युब च्यानल जीसीएस व्लगले राखेको भिडियोमा समेत प्रष्ट देखिन्छ |"},{"type":"h4","content":"प्रदर्शनको चरमोत्कर्ष र दमन"},{"type":"p","content":"बीआईसीसी पीटीजेडमा मेन गेट अगाडीको भीडको माहोल शान्त अवस्थामा रहेकोमा १३:१९ मा ३५-४० को संख्यामा वाइकसवार समूहको मेन गेट अगाडी प्रवेश भएको थियो। १३:३२ मा प्रदर्शनकारीहरूले मेन गेट अगाडी ढलेका व्यारिकेट सडकमा राखी व्यारिकेट पछाडी पम्पलेटसहित प्रदर्शन गरिरहेका थिए। यसै क्रममा १३:३४ मा नगर प्रहरी (सिटी पुलिस) को टोली गाडीबाट निस्केर शान्त प्रदर्शनकारीतर्फ बल प्रयोग गर्दै बढेको थियो भने अन्य स्थानबाट प्रहरीद्वारा व्यापक रूपमा अश्रुग्यास प्रयोग गरी भीडलाई तितरबितर गरेको देखिन्छ। केही घाइतेहरूलाई एम्बुलेन्सले उद्धार गरेको थियो। १३:३८ मा प्रदर्शनकारीको आक्रोशित भीड एकीकृत भई प्रहरीमाथि ढुंगामुडा गरेको देखिन्छ भने १३:४३ मा घाइते प्रदर्शनकारीको उद्धारका लागि दुई एम्बुलेन्स आएका थिए। संसद भवनको सामुन्ने रहेको लुम्बिनी तन्दुरी भोजनालय अगाडी एक जना घाइतेलाई सीपीआर दिइँदै गरेको देखिन्छ |"},{"type":"p","content":"बानेश्वर चोक १ सीसीटीभीमा १२:१५ मा प्रदर्शनकारीको एउटा समूह वानेश्वर चोकबाट पश्चिम गेटतर्फ लागेको थियो। १२:४२ मा प्रदर्शनकारीद्वारा प्रहरी लक्षित ढुंगा प्रहार भएको थियो भने १२:५३ मा पर्खाल चढेर रेलिङ भाँच्न सुरु भएको थियो। १३:०९ मा आन्दोलनकारीद्वारा वानेश्वर चोकमा राखिएको ट्राफिक संकेत रहेको फलामे पोलको प्रयोग गरी वीआईसीसीको वानेश्वर चोक पश्चिमतर्फको हाइपोइन्टतर्फको पर्खाल फुटाउन सुरु गरेको थियो र केही प्रदर्शनकारी संसद परिसरमा प्रवेश गरेका थिए। १३:१५ मा संसद भवन परिसरमा रहेको प्रहरी लक्षित गर्दै ढुंगा प्रहार गर्दै गर्दा एक प्रदर्शनकारीलाई गोली लागी हातले वोकेर लगिएको थियो। १३:३३ मा गोली प्रहारद्वारा घाइतेलाई व्हिलचेयरमा राखेर उद्धार गरेको देखिन्छ |"},{"type":"p","content":"१३:०० बाट लागु हुने गरी जिल्ला प्रशासन कार्यालय काठमाडौंले राष्ट्रपतिको कार्यालय शीतलनिवास, उपराष्ट्रपतिको कार्यालय लैनचौर, नारायणहिटी दरवार संग्रहालय र सिंहदरबार क्षेत्रमा कर्फ्यू क्षेत्र विस्तार गरेको थियो। १३:२० बाट अनलाइन मिडियामा पत्रकारहरू समेत घाइते भएको समाचार आएका थिए। अनलाइनखबर डटकमले १३:४० मा सिभिल अस्पतालमा उपचारका क्रममा एक जनाको मृत्यु भएको उल्लेख गरेको थियो भने रातोपाटी डटकमले १३:५४ मा एक जनाको मृत्यु र ७० जना घाइते भएको समाचार प्रकाशित गरेको थियो। सिभिल अस्पताल इमर्जेन्सी सीसीटीभी अनुसार १३:०० बजे आसपासमा गम्भीर प्रकृतिका घाइतेहरूको चाप बढेको थियो भने १३:२४ मा एक जना घाइते पत्रकार इमर्जेन्सी कक्षमा उपचारार्थ आएको देखिन्छ।"},{"type":"p","content":"अरेबिका कफी शपको सीसीटीभी अनुसार १३:२० मा गोलीले त्यहाँको अगाडीको सिसा फुटेको देखिन्छ भने वीआईसीसी पीटीजेड (अन्य सीसीटीभी क्यामेराभन्दा ४:३० सेकेन्ड ढिलो) अनुसार १३:१७ मा एक जना प्रदर्शनकारी खुट्टामा चोट लागेर भागिरहेको देखिन्छ। त्यसपछि एउटा प्रदर्शनकारीको समूह मेन गेट नजिक रहेका प्रहरीमाथि आक्रामक शैलीमा प्रस्तुत भएका थिए। सिभिल अस्पताल पीटीजेडमा १३:२१ मा प्रदर्शनकारी मेन गेटतर्फबाट घाइतेलाई उचालेर अरेबिका कफी शपतर्फ भाग्दै गरेको देखिन्छ। रोलेक्स मोटो युटुब च्यानलमा समेत अरेबिया कफी अगाडी प्रदर्शनकारीहरू गोली प्रहारबाट घाइते भएको देखिन्छ |"},{"type":"h4","content":"प्रदर्शनको अन्तिम चरणः आगजनी र थप गोली प्रहार"},{"type":"p","content":"सिभिल अस्पताल पीटीजेड र नेपाल कमर्स क्याम्पस सीसीटीमीमा १३:५६ मा युनिग्लोब पोलिक्लिनिक रहेको भवनतर्फ प्रदर्शनकारीले ढुंगा प्रहार गरेका थिए। बीआईसीसी पीटीजेडमा १४:२२ मा सशस्त्र प्रहरीको एम्बुलेन्स मेन गेट अगाडी आइपुगेको थियो र त्यसमा सवार सशस्त्र प्रहरीहरूलाई संसद परिसर भित्र पठाई प्रदर्शनकारीहरूले एम्बुलेन्समा आगो लगाइदिएका थिए। गेट अगाडी सडकमा राखिएको मृतकलाई अर्को एम्बुलेन्समा राखेर लगेको देखिन्छ।"},{"type":"p","content":"ईओएन युट्युब च्यानल अनुसार बानेघर चोकमा १४:१५-१४:३० मा एक जना विद्यार्थीलाई टाउकोमा गोली लागेको उल्लेख G| एभरेस्ट होटल बानेश्वर पीटीजेडबाट १४:१४ मा केहीलाई एम्बुलेन्सले वानेश्वर चोकबाट उद्धार गर्दै गरेको देखिन्छ भने सिभिल अस्पताल पीटीजेडबाट १४:२६ मा एक जनालाई प्रदर्शनकारीद्वारा उद्धार गर्दै गरेको देखिन्छ।"},{"type":"p","content":"ईओएन युट्युब च्यानलमा विद्यार्थीलाई टाउकोमा गोली लागेको देखिन्छ भने प्रहरी संसद भवनको पश्चिम ढोका र पानी ट्याङ्गीबीच रहेको सडकबाट सुरक्षाकर्मीले गोली प्रहार गरेको वेब खबर युट्युब च्यानलबाट देखिन्छ। नयाँ वानेधर चोक नजिक दक्षिण-पश्चिममा रहेको भवनको चौंथो तल्लामा रहेको हार्डफोर्ड कन्सल्टेन्सीमा १४:१८:१७ मा झ्यालको सिसामा गोली लागेको देखिन्छ भने नयाँ बानेश्वर चोक नजिक हार्वर्डको पूर्वी दिशामा भने संसद भवनको दक्षिण दिशामा रहेको हिमालयन जाभामा रहेका त्यसका सञ्चालकको घाँटीमा गोली लागेको पाइन्छ। बानेश्वर चोक पीटीजेडमा १४:१६ मा भीडहरू संसद भवनको पश्चिमतर्फ नयाँ वानेश्वर चोकबाट भागेको र १४:१७ मा केही घाइतेहरूलाई बोकेर लगेको देखिन्छ।"},{"type":"p","content":"१४:१० मा प्रदर्शनकारीहरू संसद भवनको दक्षिण गेटबाट हटिसकेका थिए र नयाँ वानेघर चोकमा केन्द्रित रही प्रदर्शन गरिरहेका थिए। नेपाल प्रहरी एवं सशस्त्र प्रहरीले संयुक्त रूपमा नयाँ वानेश्वरतर्फ रहेका प्रदर्शनकारीलाई लक्षित गरी फर्मेसनमा ड्युटी लिएको देखिन्छ र स्थिति नियन्त्रणमा देखिन्छ। वीआईसीसी पीटीजेडमा १५:०५ मा थाहा खबर, अरेबिका कफी अगाडी रहेका केही प्रदर्शनकारी मेन गेट अगाडी बढे सँगै नयाँ वानेश्वर चोकमा ठूलो संख्यामा रहेका प्रदर्शनकारीहरू समेत संसद गेटमा आइपुगेका थिए र सुरक्षाकर्मीले अश्वुग्यास लगायत प्रयोग गरेर प्रदर्शनकारीलाई तितरबितर बनाएका थिए। १५:१२ मा खुट्टामा गोलीद्वारा घाइते प्रदर्शनकारी देखिन्छन् भने १५:१३ मा केही घाइते प्रदर्शनकारीहरूलाई दुई वटा एम्बुलेन्सले उद्धार गरेको देखिन्छ।"},{"type":"p","content":"'बीआईसीसी पीटीजेडमा १५:५४ मा नेपाली सेनाको टोली गाडीसहित संसद भवनको मेन गेटमा आइपुगेपछि नयाँ बानेध्र चोकमा रहेका प्रदर्शनकारी सुरक्षाकर्मीहरूको सुरक्षा फर्मेसन तोड्दै मेन गेटमा आइपुगेका थिए। गेटमा प्रदर्शनकारी चढ्ने तथा तोड्ने प्रयास गरेपछि १५:५९ मा सुरक्षाकर्मीले त्यहाँ जम्मा भएको भीडलाई तितरबितर बनाएका थिए। १६:०९ मा एक जना घाइते महिला प्रदर्शनकारीलाई प्रदर्शनकारीहरूले बोकी सिभिल अस्पतालतर्फ लग्दै गरेको देखिन्छु।"},{"type":"h4","content":"प्रदर्शनको समापनः स्थिति सामान्यीकरण"},{"type":"p","content":"१६:०५ सम्ममा सुरक्षाकर्मीले संसद परिसर नजिकबाट प्रदर्शनकारीहरूलाई हटाइसकेको अवस्था देखिन्छ भने प्रदर्शनकारीको समूह पनि पातलो भइसकेको थियो। केही प्रदर्शनकारीहरू सिभिल अस्पताल तथा नेपाल कमर्स क्याम्पस गेट नजिक रहेका देखिन्छन् भने अर्को प्रदर्शनकारीको समूह भने एभरेस्ट होटल अगाडी देखिन्छन्।"},{"type":"p","content":"१६:३४ मा नेपाली सेनाको टोली गाडीसहित एभरेस्ट होटेल अगाडी आएपछि त्यहाँ रहेका प्रदर्शनकारीहरूलाई प्रहरीले विजुलीबजारतिर लखेटेको थियो। १७:३० मा प्रहरी सिभिल अस्पताल गेटतिर गई त्यहाँ रहेका प्रदर्शनकारीहरूलाई हटाएको थियो। १८:१५ मा नयाँ वानेश्वर संसद परिसर क्षेत्रको अवस्था सामान्य देखिन्छु |"},{"type":"p","content":"(+Source: छभतमाडत/उपत्यका प्रहरी कार्यालय सिसिटिभि फुटेज/0ला४ valley Police, Harddisk1/Civil hospital, Harddisk1/f3f¥e स्रोतहरूबाट प्राप्त सोसियल मिडिया लिंकहरू /Social Media/Arabia Coffee, Hardford, Himalayan Java https://www.onlinekhabar.com/interactive/interactive-protest-timeline.html )"},{"type":"p","content":"Youtube Channel : https://www.youtube.com/@eon_nepal"},{"type":"p","content":"Video Links : https://www.youtube.com/watch?v=8MSs6d_4rh4"},{"type":"h4","content":"नेपालमा अनियन्त्रित सामाजिक सञ्जालका रणनीतिक जोखिमहरू"},{"type":"p","content":"नेपालको द्रुत डिजिटल रूपान्तरणले सामाजिक लाई सार्वजनिक छलफल, नागरिक सहभागिता, सूचनाको प्रवाह, र विचार अभिव्यक्तिको केन्द्रका रुपमा स्थापित गरिदिएको छ । यसले अभिव्यक्ति, जनचेतना, र वास्तविक समयमै जानकारी प्राप्त गर्ने अवसरहरू विस्तार गरेको छु । Digital Technology ले अध्ययन-अध्यापन, रिसर्च तथा व्यजसाय गर्न, व्यवसायका विविधिकरण र प्रचार- प्रसारमा पनि सहयोग पुर्याएको छ। नेपाल दूरसञ्चार प्राधिकरणका अनुसार, देशको ब्रडब्यान्ड पहुँच १३१.५१% र मोबाइल फोन पहुँच १३८.६२% पुगेको छ | जनसंख्याभन्दा बढी रहेको यो पहुँचले सामाजिक सञ्जाल र अनलाइन प्लेटफर्महरूको व्यापक प्रभाव स्पष्ट रूपमा देखाउँछ । तर, यि सञ्जाल तथा प्लेटफर्महरूको प्रभावकारी नियमनको अभावले यी प्लेटफर्महरूलाई व्यक्तिको विश्वसनीयता निर्माण वा ध्वस्त पार्ने शक्तिशाली साधनमा पनि रूपान्तरण गरिदिएको छ। सार्वजनिक धारणा प्रायः प्रमाणित तथ्यभन्दा बढी योजनाबद्ध कथन, सिर्जित भावनात्मक सामग्री, र समन्वित डिजिटल अभियानका आधारमा निर्माण हुने गरेको छ, जसले डिजिटल हेरफेरमा सक्षम केही पक्षहरूले आफु अनुकुल प्रयोग गर्न सहयोग पुर्याएको छ । म्यान्मारमा पत्रकार, मानवअधिकार संस्थाहरू, र संयुक्त राष्ट्रसंघीय तथ्य-अनुसन्धान मिसनको अनुसन्धानले फेसबुकमा व्यापक रूपमा घृणात्मक र उकास्ने सामग्री लगातार दोहोर्याइने र एल्गोरिदमिक रूपमा प्रवर्धन गरिने कार्यवाट रोहिर्या समुदाय विरुद्ध हिंसा व्यापक बनेको देखायो । यसले हालेको इतिहासकै सबैभन्दा ठूलो शरणार्थी संकटमध्ये एक निम्त्यायो, जसले अनियन्त्रित डिजिटल प्लेटफर्महरूले कति विनाशकारी परिणाम निम्त्याउन सक्छन् भन्ने स्पष्ट गर्छ ।"},{"type":"p","content":"हालैका आन्तरिक घटनाहरू, विशेषगरी Gen-z प्रदर्शनले सामाजिक सञ्जाल मार्फत प्रवाह भएका भ्रामक जानकारी र भावनात्मक सामग्रीले कसरी छिटो तनाव बढाउन सक्छ भन्ने क्रालाई झनै प्रस्ट पारेको छ। आन्तरिक तथा बाह्य स्रोतबाट प्रवर्धन गरिएका गलत कथनहरू ठूलो परिमाणमा फैलिन पुगे, जसले जनसमूहको तीब्र परिचालन, सार्वजनिक तथा निजी सम्पत्तिमा क्षति, र समग्र सामाजिक अस्थिरता निम्त्यायो। यस्ता घटनाहरूले अनियन्त्रित डिजिटल सामग्री प्रवाहका कारण राज्यका संरचनालाई दबाबमा पार्न, सामाजिक स्थिरतालाई कमजोर बनाइदिन, र स्थानीय असन्तुष्टिलाई देशव्यापी संकटमा बदल्न सक्ने गम्भीर जोखिम रहेको देखाउँछ ।"},{"type":"p","content":"यी जोखिमहरू न्यूनीकरण गर्न नेपालले डिजिटल जोखिम व्यवस्थापनका लागि संस्थागत क्षमता सुदृढ गर्नुपर्छ। यसमा सामाजिक सञ्जाल गतिविधि निगरानी, Emerging Digital Threat पहिचान, र दुष्प्रचार अभियानहरूको समयमै प्रत्युतर दिन सक्षम बनाउने गरी साइवर ब्युरोको क्षमता विस्तार गर्नु अति आवश्यक छ । त्यस्तै, सामाजिक सञ्जाल-सृजित अपराधको प्रमाण विश्लेषण गर्न डिजिटल फरेन्सिक प्रयोगशालाहरूले आवश्यक उपकरण, दक्ष जनशक्ति, र प्राविधिक क्षमताका साथ विश्वसनीय विश्लेषण गर्ने दक्षता कायम गर्न सक्नुपर्छ | यससँगै, मध्यस्थ संस्थाको जवाफदेहिता, आपत्तीजनक/गैरकानूनी सामग्री हटाउने प्रक्रियाको पारदर्शिता, आधुनिक साइबर कानुन, र राष्ट्रिय डिजिटल साक्षरता जस्ता सुधार अनिवार्य छन्, ताकि सामाजिक सञ्जालले लोकतान्त्रिक स्थिरतालाई सुदृढ गर्न सहयोग पुर्याओस |"},{"type":"p","content":"सूचना स्वयं शक्ति बनेको वर्तमान परिवेशमा सामाजिक सामज्जस्य, सार्वजनिक सुरक्षा, र लोकतान्त्रिक मजबूती जोगाउन डिजिटल प्रविधि माथी सामाजिक सदभाव कायम राख र व्यक्तिको मर्यादा अक्षण राख्न व्यावहारिक हस्तक्षेप गर्नु अत्यावश्यक छ |"}]