[{"type":"p","content":"'जनरल जेड माडागास्कर' नामक फेसबुक पेज आन्दोलनको लागि प्राथमिक आयोजक केन्द्रको रूपमा देखा परेको थियो। सेप्टेम्बर २५ देखि, सुरक्षा बलको प्रयोग र लुटपाटका कारण प्रदर्शनकारी र नागरिकहरू सहित २२ जनाको मृत्यु भएको थियो। प्रमुख शहरहरूका व्यावसायिक क्षेत्रहरू र सार्वजनिक सुविधाहरूमा लुटपाट र तोडफोड भएको थियो। सेप्टेम्बर २६ मा आफ्नो उर्जा मन्त्रीलाई हटाएपछि, मालागासी राष्ट्रपति एन्ड्री राजोएलिनाले सेप्टेम्बर २९ मा प्रधानमन्त्री क्रिश्चियन न्त्सेको सरकार विघटनको घोषणा गरे। ६ अक्टोबर २०२५ मा उनले सैन्य जनरल रुफिन जाफिसाम्बोलाई नयाँ प्रधानमन्त्री नियुक्त गरे। अक्टोबर ११ मा, माडागास्कर सशस्त्र बलका एकाइहरूले विरोध प्रदर्शनको समर्थनमा एक सैनिक विद्रोह गरे।"},{"type":"h4","content":"मेक्सिको"},{"type":"p","content":"सन् २०२५ नोभेम्बर १५ मा, हजारौंले मेक्सिकोभरि 'जेनेरसन जेड' को ब्यानरमा विरोध प्रदर्शन गरे। नोभेम्बर महिनाको सुरुमा अपराध विरोधी उरुपान मेयर कार्लोस मान्जोको सार्वजनिक हत्यापछि बढ्दो हिंसाको निन्दा गर्दै मेक्सिको सिटीमा, हुड लगाएका प्रदर्शनकारीहरूको सानो समूहले राष्ट्रपति क्लाउडिया शेनबाउम बस्ने राष्ट्रिय दरबार वरिपरिको बार भत्काए। जसले गर्दा दंगा प्रहरीसँग झडप भयो। यस विरोधमा करिब १०० प्रहरी अधिकारी घाइते भए र २० जना नागरिक पनि घाइते भए। मेक्सिकोका विभिन्न शहरहरूमा अन्य जुलुसहरू भए। मेक्सिको सिटीका केही प्रदर्शनकारीहरूले 'बाहिर, मोरेना' नारा लगाउँदै शेनबाउमको पार्टीमाथि आफ्नो आक्रोश निशाना बनाए। कतिपयले अपराध र हिंसा रोक्न राज्यको बलियो प्रयासको लागि पनि आह्वान गरे ।"},{"type":"p","content":"'जेनेरसन जेड मेक्सिको' भनेर चिनिने एउटा समूहले सामाजिक सञ्जालमा सञ्चार 'घोषणापत्र' मा भनेको छु कि यो निष्पक्ष छ र हिंसा, भ्रष्टाचार र शक्तिको दुरुपयोगबाट वाक्क भएका मेक्सिकन युवाहरूको प्रतिनिधित्व गर्दछ। युवाद्वारा परिचालित यो आन्दोलन शान्तिपूर्ण रूपमा अगाडि बढ्यो तर पछि केही व्यक्तिहरूले हिंसात्मक कार्यहरू गर्न थाले ।"},{"type":"p","content":"राष्ट्रपति क्लाउडिया शेनबाउमले भनिन् कि मार्चको आह्वान उनको विरुद्धमा सशुल्क डिजिटल अभियानद्वारा समर्थित छ। जुन विपक्षी राजनीतिक र व्यावसायिक व्यक्तिहरुको समर्थनमा भएको हो भन्ने आरोप लगाइन ।"},{"type":"h4","content":"फिलिपिन्स"},{"type":"p","content":"फिलिपिन्समा जिएनजेड आन्दोलन युवा नेतृत्वको विरोध प्रदर्शनको एक श्रेंखला हो। यो मुख्यतया व्यापक सरकारी भ्रष्टाचार, आर्थिक असमानता र अवसरको अभावको क्रोधबाट प्रेरित भएको पाइन्छु। यो आन्दोलन नक्कली वाढी-राहत परियोजनाहरू समावेश गर्ने कथित बहु-अरव डलरको भ्रष्टाचार काण्डबाट सुरु भएको थियो। प्रदर्शनकारीहरूले सार्वजनिक कोषको प्रयोगमा जवाफदेहिता र पारदर्शिताको माग गरिरहेका थिए। आन्दोलनको अर्को मुख्य पाटो वेरोजगारी, वढ्दो आर्थिक असमानता र आम मानिसहरूले सामना गरिरहेको महंगी आदि थिए। आन्दोलनको माग राजनीतिक जवाफदेहिता, नातावाद र शक्तिको दुरुपयोगको अन्त्य रहेको थियो । जिएनजेडका कार्यकर्ताहरूले रेडिट, भ्रेड र डिस्कर्ड जस्ता सामाजिक मिडिया फोरमहरू प्रयोग गरेको पाइन्छ। फिलिपिन्समा नीति सुधारहरूमा दीर्घकालीन प्रभाव देख बाँकी नै छ।"},{"type":"h4","content":"हङकङ"},{"type":"p","content":"प्रस्तावित सुपुर्दशि विधेयकले, हङकङवासीहरूलाई चीनको अपारदर्शी कानुनी प्रणाली र राजनीतिक उत्पीडनमा पार्न सक्छ भन्ने कुराले आन्दोलन गर्न युवाहरुलाई उत्प्रेरित गर्यो। यस आन्दोलनमा सुपुर्दगि विधेयक प्रहरी क््रताको स्वतन्त्र अनुसन्धान, पक्राउ परेका प्रदर्शनकारीहरूमाथिको आरोप फिर्ता लिने र हङकङका कार्यकारी प्रमुखको लागि प्रत्यक्ष चुनाव गर्ने माग राखिएका थिए।"},{"type":"p","content":"यो आन्दोलन विशाल शान्तिपूर्ण मार्चको रूपमा सुरु भयो तर सरकारी हट र प्रहरी दमनका कारण हिंसात्मक बन्यो जसका कारण प्रहरीसँग टकराव, सरकारी भवनहरूको घेरावन्दी र विमानस्थल अवरोध निम्त्यायो। यस आन्दोलनले अनलाइन समन्वय, हडताल र भौतिक अवरोधहरू जस्ता मुख्य प्रदर्शनका कार्यहरू गरिएका थिए। यस प्रदर्शनमा प्रदर्शनकारीहरूले प्रर्दशनका लागि समन्वय गर्न र विश्वव्यापी समर्थन जुटाउन सामाजिक सञ्जालको व्यापक प्रयोग गरेका थिए।"},{"type":"p","content":"यस आन्दोलनले सरकारप्रतिको गहिरो अविश्वास उजागर गन्यो। गम्भीर राज्य दमन निम्त्यायो। जसको परिणाम स्वरुप सन् २०२० मा उक्त बिधेयक कानूनमा पारित भयो जसले आन्दोलन समाप्त गरिदियो।"},{"type":"p","content":"माथि उल्लिखित विभिन्न देशहरुमा घटित जिएनजेड आन्दोलनको निचोडले के देखाउँछ भने कुनै पनि जनआन्दोलन र संघर्षको मूल कारण राजनैतिक कुसस्कार, प्रशासनिक ढिलासुस्ती, बढ्दो भ्रष्टाचार, निरन्तरको मूल्य वृद्धि, शैक्षिक बेरोजगारी, श्रोतको कृशल विनियोजन हुन नसक्नु, वर्गीय रुपमा असमानता कायम रहनु साथै राज्यशक्तिको मूलधारमा सीमित वर्गको आधिपत्य कायम रहनु नै हो। विशेष गरी शासनसत्ताको वागडोर सम्हालेका नेतृत्वपङ्ति तटस्थ, व्यवसायिक, निष्ठावान, पारदर्शी र उत्तरदायी हुनु अपरिहार्य हुन्छ। शासनपद्धति जस्तोसुकै नामाकरणको भएतापनि यसका सञ्चाकलकर्ताहरुको सक्षमता र जनउत्तरदायित्वले यसको सफलता र असफलताको मापन गर्दछ। विश्व परिवेशको अध्ययन गर्दा समेत विभिन्न देशमा राजनीतिक नेतृत्व दीर्घकालसम्म एकै व्यक्ति/समूह शासन सञ्चालनमा रहिरहदाँ जनमानसमा असन्तुष्टि बढेको पाइन्छ।"},{"type":"h4","content":"नेपालमा जिएनजेड (Generation Z) आन्दोलन:"},{"type":"p","content":"खासगरी पुरानो डेट एक्स्पाए्ड अर्थात् म्याद सकिएको पुस्ताको राजनीतिक एकाधिकार, युवा पुस्तामा राजनीति हस्तान्तरण गर्न नसक्नु जस्ता शासनशैली, र सामाजिक संस्चनाबाट असन्तुष्ट युवाहरूले वैकल्पिक सोच र कार्यशैली अपनाएका छन्।यो पुस्ता राज्यप्रति आलोचनात्मक मात्र होइन, समाधानमुखी र नवप्रवर्तनशील पनि देखिन्छ। यो पुस्ता नेपालमासमेत नयाँ सोच, नयाँ प्रविधि, र परिवर्तनको चेतनासँग उदाएको छ। नेपालमा जियनजेड भनिने पुस्ता अहिले देशको सामाजिक, सांस्कृतिक, आर्थिक र राजनीतिक जीवनका सक्रिय अंग बनिरहेका छन्।"},{"type":"image","content":"/images/protest.jpeg","alt":"नारा लगाएर विरोध प्रदर्शन ब्यानर","caption":"विरोध नारा प्रदर्शन ब्यानर"},{"type":"p","content":"सूचना प्रविधिको तीत्र विस्तार, इन्टरनेटको सुलभता, र मोबाइल प्रविधिको सहज पहुँचले नेपाली जिएनजेडलाई विश्व समुदायसँग प्रत्यक्ष रूपमा जोड्ने माध्यम उपलब्ध गराएको छ। त्यसकै परिणामस्वरूप उनीहरू विश्वका समकक्षी युवाहरू जस्तै स्वतन्त्र विचार, स्वतन्त्र अभिव्यक्ति, र समान अवसरको माग गर्दै अघि बढिरहेका छन्। राजनीतिक क्षेत्रमा पनि यो पुस्ताले पुरानो सोचप्रति प्रश्न उठाउँदै नयाँ प्रकारको राजनीतिक चेतना फैलाएको छ। जुन पारदर्शिता, जवाफदेहिता र परिणाममुखी नेतृत्वमा आधारित छ। सामाजिक सञ्जालमार्फत उनीहरूले नागरिक आन्दोलनहरूमा निर्णायक भूमिका खेलेको पाइन्छ। आन्दोलन हुनुभन्दा केही समय अघि देखि नै विभिन्न सामाजिक सञ्जालमार्फत Nepo Kids, Nepobaby, Enough is enough, No not again, Anti-corruption जस्ता अभियानहरु सञ्चालन भएको देखिन्छु।"},{"type":"image","content":"/images/student_protest.png","alt":"सडकमा बसेर विरोध प्रदर्शन गर्दै विद्यार्थीको समूह","caption":"सडकमा बसेर विरोध प्रदर्शन गर्दै विद्यार्थीको समूह"},{"type":"p","content":"यसरी हेर्दा, नेपालमा जियनजेडको उदय केवल एक पुस्ताको परिवर्तन होइन, यो सोच, प्रविधि, र मूल्य प्रणालीको पुनर्जागरण पनि हो। यस पुस्ताले शासन व्यवस्थामा सुधार, सामाजिक समानता र दिगो भविष्य निर्माणको लागि नयाँ दृष्टिकोण र व्यवहार प्रस्तुत गरेको छ। भाद्र २३ र २४ गतेको आन्दोलन यिनै प्रवृति प्रतिको विरोधका रुपमा देखिएको छ तथापि, यसको सुरुवात भने सरकारले गरेको सामाजिक सञ्जालको बन्दको निर्णय प्रारम्भिक कारकका रुपमा रहेको पाइन्छ। जसले युवाहरुलाई आन्दोलन गर्न उत्प्रेरित गरी उर्जा प्रवाह गर्यो ।"},{"type":"image","content":"/images/people_with_banner.png","alt":"ब्यानर बोकेर विरोध प्रदर्शन गरिरहेका समूह","caption":"ब्यानर बोकेर विरोध प्रदर्शन गरिरहेका समूह"},{"type":"h4","content":"सामाजिक सञ्जल बन्द उपरको सनुवुाईमा सवोच्च अदालतको आदेश पश्चात विकासित घटनाक्रम:"},{"type":"p","content":"पछिल्लो आन्दोलनको विजारोपण नेपाल सरकारद्वारा मिति २०८२ ।५।९ मा नेपालमा दर्ता नगरेका २६ वटा सामाजिक सञ्जाल प्लेटफर्महरु वन्द गर्ने निर्णय विरुद्ध युवा जमात विशेष गरी जियनजेड पुस्ताको आक्रोश र आपत्ति रहेको देखिन्छ। नेपाल सरकार सञ्चार तथा सूचना प्रविधि मन्त्रालयले तोकेको सामाजिक सञ्जाल दर्ता गर्ने सम्बन्धी नियमहरूको पालना गर्न असफल भएको भन्दै विभिन्न"},{"type":"p","content":"जस अन्तर्गत Facebook - Social Media, Facebook Messenger - Messaging, Instagram - Social Media, WhatsApp - Messaging, YouTube - Video Sharing, X (Twitter) - Microblogging, LinkedIn - Professional Network, Snapchat - Social Media, Reddit - Community Forum, Discord - Messaging / Community, Pinterest - Visual Discovery, Signal - Messaging, Threads - Microblogging, WeChat - Messaging / Social, Quora - Q&A Community, Tumblr - Blogging / Social, Clubhouse - Audio Chat, Mastodon - Microblogging, Rumble - Video Sharing, MeWe - Social Media, VK (VKontakte) - Social Media, Line - Messaging, IMO - Messaging, Zalo - Messaging, Soul - Social Networking, Hamro Patro - Local Nepali App जस्ता सामाजिक सञ्जालहरु रहेका थिए। तत्कालीन सरकारका प्रवक्तासमेत रहेका सञ्चार तथा सूचना प्रविधि मन्त्री पृथ्वीसुव्बा गुरुङले प्रतिबन्धलाई 'कानूनी' भनेर औचित्य दिन तीन कारणहरू प्रस्तुत गरे। पहिलो, 'सामाजिक सञ्जालको प्रयोगलाई नियमन गर्ने निर्देशिका २०८०', दोस्रो मिति २०८२। ५। १९ मा बसेको मन्त्रिपरिषद् बैठकको निर्णय र तेस्रो सर्वोच्च अदालतको मिति २०८१। ०६। १३ को फैसला। मन्त्रालयद्वारा जारी प्रेस विज्ञप्तिमा भनिएको छः ‘अदालतको अवहेलना मुद्दा (मुद्दा नं. ०८०-CF-००१२) मा सम्मानित सर्वोच्च अदालतको पूर्ण इजलासले नेपाल सरकारलाई विदेशी र स्वदेशी मूलका अनलाइन र सामाजिक सञ्जाल प्लेटफर्महरूलाई सञ्चालन गर्नु अघि सक्षम अधिकारी समक्ष दर्ता अनिवार्य गर्न निर्देशनात्मक आदेश दिएको छ, ताकि अवान्छित सामग्रीको मूल्याङ्कन र अनुगमन गर्न सकियोस्। ‘ सर्वोच्च अदालतको सो आदेशमा सीधाक्रा डट कमद्वारा प्रकाशित डार्क फाइल रिपोर्ट सम्बन्धी अदालतको अवहेलनाको मुद्दासँग सम्बन्धित छ। यस मुद्दामा सर्वोच्च अदालतका ९ जना न्यायाधीशहरूको पूर्ण इजलासले उक्त फैसलाले स्वदेशी तथा विदेशी उत्पत्तिका अनलाइन तथा सामाजिक सञ्जाल प्लेटफर्महरुलाई सञ्चालन पूर्व अनिवार्य रुपमा साधिकार निकायमा सूचीकरण गर्न गराउन नेपाल सरकारको नाममा निर्देशनात्मक आदेश जारी गरेको थियो।"},{"type":"h3","content":"अदालतको उक्त फैसलामा मुख्यतः निम्न तीन कुरा उल्लेख गरिएको पाइन्छः"},{"type":"list","list-type":"number","content":[{"no":"१","content":"स्वदेशी तथा विदेशी दुवै अनलाइन र सामाजिक सञ्जाल प्लेटफर्महरूले देशमा सञ्चालन गर्नु अघि सम्बन्धित निकायमा दर्ता गर्नुपर्छ।"},{"no":"२","content":"सरकारले यी प्लेटफर्महरूको निरीक्षण र नियमन गर्न प्रेस काउन्सिल नेपाल जस्तै नियामक निकाय सिर्जना गर्न कानून बनाउनुपर्छ।"},{"no":"३","content":"नयाँ नियमहरूमा सामाजिक सञ्जालमा अवाञ्छनीय सामग्रीको मूल्याङ्कन र निगरानी गर्ने संयन्त्रहरू समावेश हुन्पर्छ।"}]},{"type":"p","content":"भाद्र ९ गतेको मन्त्रिपरिषद्को निर्णय र भाद्र १९ गतेको सञ्चारमन्त्रीस्तरीय निर्णयअनुसार नेपालमा सूचीकरण नभएका सामाजिक सञ्जाल निष्क्रिय बनाउन दूरसञ्चार प्राधिकरणले सोही दिन मोबाइल तथा इन्टरनेट सेवा प्रदायकहरूलाई पत्राचार गरेको थियो । भदौ २० गते देखि २६ वटा सामाजिक सञ्जाल निष्कृय गरिएका थिए।"},{"type":"p","content":"सरकारले सर्वोच्चको व्याख्याकै अपव्याख्या गरेर सामाजिक सञ्जाल बन्द नै गरिदिएको थियो । सर्वोच्च अदालतको निर्देशन उल्लेख गर्दै, सरकारले दर्ता नगरिएका सामाजिक सञ्जाल प्लेटफर्महरूलाई प्रतिबन्ध लगाउने सरकारको निर्णय विरुद्ध अधिवक्ता डा. सुनिलरंजन सिंह लगायतका रिट निवेदनहरु दायर गरिएका थिए। ती निवेदनहरु दर्ता नै नगरी सर्वोच्च अदालत प्रशासनले दरपीठ गरी दिएको थियो। सर्वोच्च प्रशासनले पनि फैसलाको अपव्याख्या गरेर सरकारको निर्णयलाई समर्थन गरेको थियो । सर्वोच्च अदालतका रजिष्ट्रार मानबहादुर कार्कीले गरेको सो दरपीठ उपर परेको निवेदनमा आन्दोलनको दोस्रो दिन भदौ २४ गते दर्ता हुने गरी इजलासबाट आदेश भएको थियो ।"},{"type":"p","content":"खासमा वि.सं.२०८२ साल भदौ २३ र २४ गते भएको जिएनजेड पुस्ताको आन्दोलनको सुरुवात, 5०21 1९09 माथि सरकारको सामाजिक सञ्जाल बन्द गर्ने निर्णयको विरोधमा भएको देखिएता पनि यस संघर्षको मूल जड भने युवा पुस्ताको राजनीतिक विसंगति प्रतिको विद्रोह थियो। राजनीतिक नेतृत्वमा एकै थरी र समूहको बारम्बार हुने हस्तक्षेप, प्रशासनको स्वच्छतामाथिको प्रश्न, न्यायालयमाथिको घट्दो विश्वास, अपारदर्शी उत्तरदायित्वविहिन निजी क्षेत्र, संगठनको रुपमा विकास भएको नागरिक समाज, सार्वजनिक श्रोतमाथि सीमित व्यक्तिको दोहन, नकरात्मकताको सन्देश फैलाउने केही पत्रकार पनि यसका कारकको रुपमा देखिएका छन्।"},{"type":"p","content":"हेरेक सफल कहलिएका मुलुकहरुमा निष्ठावान राजनैतिक प्रणाली, प्रभावकारी स्वतन्त्र प्रशासन उत्तरदायी निजी क्षेत्र र तटस्थ नागरिक समाजको सिद्धान्त अवलम्बन गरेको हुन्छ। परम्परागत कार्यशैली र प्रणालीलाई सहज, प्रभावकारी र मितव्ययी बनाउन सूचना प्रविधिको विस्तार र त्यसको प्रयोगबाट नै सम्भव हुन्छ। अझ पछिल्लो समयमा त Digital Platform को प्रयोग आम युवा जमातको व्यवसायिकताको आधार बनेको छ। प्रविधिको तीत्र विकाससँगै सञ्चारको सरल माध्यमको रुपमा बनाइएका सामाजिक सञ्जालहरु त Digital Job Creator को रुपमा स्थापित भएका छन्। प्रविधिको विकास निरन्तर प्रक्रिया हो। यसले हाम्रो जीवनमा प्रत्यक्ष अथवा परोक्ष रुपमा प्रभाव पारिरहेको हुन्छ। तसर्थ, हामीले हिजो बिताएको जीवनशैली र आजको पुस्ताको जीवनशैलीबीच निकै अन्तर छ।"},{"type":"p","content":"भाद्र २३ र २४ गते जिएनजेड पुस्ताद्वार भएको आन्दोलनको क्रममा भएका घटनाहरुको प्राप्त कार्यदेश बमोजिम यस आयोगले निष्पक्षता, जवाफदेहिता, पारदर्शिता, विश्वसनीयता र नैतिकताको 'कसीमा रही निर्दिष्ट ढाँचामा प्रतिवेदन तयार गरेको छ।"},{"type":"h2","content":"परिच्छेद - २ : जाँचबुझ आयोगको गठन, काम, कर्तव्य, अधिकार र कार्यविधि:"},{"type":"h3","content":"२.१. जाँचबुझ आयोगको गठनः"},{"type":"p","content":"नेपाल सरकार, मन्त्रिपरिषद्ले जाँचबुझ आयोग ऐन २०२६ को दफा ३ को उपदफा (२) ले दिएको अधिकार प्रयोग गरी नेपालको राष्ट्रहित, सुशासन तथा भ्रष्टाचार नियन्त्रण लगायतका माग राखी जियनजेड युवा पुस्ताद्वारा संवत् २०८२ साल भदौ २३ र २४ गते गरेको प्रर्दशनको क्रममा काठमाडौं लगायत विभिन्न भागमा भएका भौतिक तथा मानवीय क्षतिको यथार्थ छानविन गरी प्रतिवेदन पेश गर्न जाँचबुझ आयोग गठन गरेकोले सोही दफाको उपदफा (३) बमोजिम यो सूचना जारी गरिएको छ भनी मिति २०८२। ०६। ०५ को राजपत्रको भाग ५ खण्ड ७५ अतिरित्ताङ्ग २८ मा सूचना प्रकाशित गरी आयोगको गठन भएको हो। उक्त राजपत्रमा आयोग गठन सम्बन्धमा भएको व्यहोरा देहाय बमोजिम रहेको छ।"},{"type":"h3","content":"२.२. जाँचबुझ आयोगको संरचनाः"},{"type":"list","list-type":"number","content":[{"no":"(क)","content":"श्री गौरीबहादुर कार्की, पूर्व अध्यक्ष विशेष अदालत - अध्यक्ष ।"},{"no":"(ख)","content":"श्री विज्ञान राज शर्मा, पूर्व प्रहरी अतिरिक्त महानिरीक्षक - सदस्य ।"},{"no":"(ग)","content":"श्री विश्वेश्वर प्रसाद भण्डारी, अधिवक्ता अन्तराष्ट्रिय अपराध अनुसन्धान विज्ञ - सदस्य ।"}]},{"type":"h3","content":"२.३. आयोगको क्षेत्राधिकार र जिम्मेवारी:"},{"type":"list","list-type":"number","content":[{"no":"(क)","content":"वि.सं. २०८२ साल भदौ २३ र २४ गते काठमाडौं लगायतका मुलुकका विभिन्न भागमा प्रदर्शनका क्रममा भएको भौतिक एवं मानवीय क्षतिको यथार्थ छानविन गर्ने ।"},{"no":"(ख)","content":"घटना घट्नुको कारणका सम्बन्धमा जाँचबुझ गरी सोको यकीन राय सुझाव सहितको प्रतिवेदन पेश गर्ने ।"},{"no":"(ग)","content":"भौतिक एवं मानवीय क्षतिसँग सम्वन्धित सूचना वा निवेदन ग्रहण गरी विश्लेषण गर्ने र कारबाहीको सम्बन्धमा आवश्यक राय दिने ।"},{"no":"(घ)","content":"भविष्यमा यस्ता घटना दोहोरिन नदिन अपनाउनुपर्ने उपाय तथा सुझावहरु पेश गर्ने ।"},{"no":"(ङ)","content":"प्रतिवेदनमा उल्लेख भएका सुझावहरु कार्यान्वयनका लागि स्पष्ट कार्ययोजना प्रस्तुत गर्ने ।"}]},{"type":"h3","content":"२.४. जाँचबुझ आयोगको कार्यप्रणाली:"},{"type":"list","list-type":"number","content":[{"no":"(क)","content":"आयोगलाई जाँचबुझ आयोग ऐन, २०२६ बमोजिम आफ्नो कार्य सम्पादन गर्नेछ ।"},{"no":"(ख)","content":"आयोगले स्वतन्त्र र निष्पक्ष ढंगले कार्य गर्नेछु र कसैको दवाव वा प्रभावमा पर्ने छैन ।"}]},{"type":"h3","content":"२.५. जाँचबुझ आयोगको समयावधि र जनशक्ति:"},{"type":"list","list-type":"number","content":[{"no":"(क)","content":"आयोगले कार्य प्रारम्भ भएको मितिले ३ महिनाभित्र राय सहितको प्रतिवेदन नेपाल सरकार समक्ष पेश गर्नेछ ।"},{"no":"(ख)","content":"आयोगको कार्यालयमा आवश्यक पर्ने कर्मचारी सहसचिव-१, उपसचिव-१, शाखा अधिकृत-१, नायबसुब्बा-१, कम्प्युटर अपरेटर-१, हलुका सवारी चालक-१ र कार्यालय सहयोगी-१ गृह मन्त्रालयले उपलब्ध गराउने ।"},{"no":"(ग)","content":"नेपाल सरकार मन्त्रिपरिषद्को मिति २०८२।०७।२५ गतेको निर्णयबमोजिम आयोगमा कर्मचारी थप गर्ने स्वीकृति भई निजामती र नेपाल प्रहरी समेत गरी १५ जनाले कार्य गरिरहेको ।"},{"no":"(घ)","content":"यस आयोगलाई आफ्नो कार्य सम्पादन गर्न सुरुमा तीन महिनाको कार्य अवधि तोकीएकोमा कार्यबोझ र समय अभावले गर्दा मिति २०८२/०९/०३ गते प्रथम पटक एक महिनाको लागी, त्यसपछि क्रमश दोस्रो र तेस्रो पटक मिति २०८२/१०/०८ गते बीस दिन र मिति २०८२/१०/२६ गते पच्चीस दिनको लागी कार्य अवधि थप गरीएको थियो ।"}]},{"type":"h3","content":"२.६.आयोगको कार्यविधि:"},{"type":"p","content":"जाँचबुझ आयोग ऐन, २०२६ को दफा ठ ले ऐन र ऐन अन्तर्गत बनेका नियमको अधीनमा रही आयोगले 'काम कारबाहीको लागि कार्यविधि आफै बनाउन सक्नेछु भन्ने व्यवस्था गरेबमोजिम आन्तरिक कार्य सम्पादनको लागि आयोगले आवश्यकता बमोजिम निर्णय गरी प्रतिवेदन तयारीको कार्य गरियो ।"},{"type":"h2","content":"परिच्छेद - ३: तथ्य तथा तथ्याङ्क संकलनमा प्रयोग गरिएका विधिहरु"},{"type":"p","content":"तोकिएको कार्यदिश अनुसार कार्य सम्पादन गर्न सूचना संकलनको लागि आयोगका अध्यक्ष र सदस्यहरुको नेतृत्वमा उपत्यका र देशका बढी क्षतिग्रस्त जिल्लाहरु कास्की, चितवन, कैलाली, कञ्चनपुर, सुर्खेत, झापा, बारा, पर्सा, सुनसरी, रुपन्देही लगायतकासँग (प्रत्येक जिल्लामा गएको सदस्यको नाम र मिति सहित उल्लेख गर्ने) सरकारका तर्फबाट र प्रर्दशनकारीको तर्फबाट भएका मानवअधिकार उलङ्घनका घटनाहरुको सन्दर्भमा विषय विज्ञ मानवअधिकार आयोग नागरिक समाजका प्रतिनिधि सञ्चारकर्मी र कानूनका वेत्ताहरुसँग समेत छलफल र अन्तरक्रिया गरेको थियो। विभिन्न राजनैतिक दल र व्यक्तिगत रुपमा निजी सम्पत्ति क्षति भएका व्यक्तिहरु आयोगमा आई घटनाको सन्दर्भमा जानकारी समेत दिएका थिए। यस्तै आयोगले जाँचबुझ आयोग ऐनले तोकेको सीमाभित्र रही विभिन्न सरकारी सार्वजनिक निकायहरुबाट रेकर्डहरु झिकाई अध्ययन र विश्लेषण समेत गरेको थियो। प्राप्त तथ्य र तथ्याङ्कको आधारमा प्रर्दशनको क्रममा उत्तरदायी रहेका सरकारी पदाधिकारीका साथै अन्य सम्बद्ध व्यक्तिहरुलाई सोधपुछ र छलफल गरी प्राकृतिक न्यायको सिद्धान्त बमोजिम बयान कार्य समेत गरिएको छ। साथै उद्योगी व्यवसायी निजी प्रतिष्ठानहरुका व्यक्तिहरु र संस्थागत रुपमा समेत अन्तरक्रिया गरिएको छ। प्रतिवेदन तयार पार्नको लागि आवश्यक तथ्याङ्ग संकलनमा प्रयोग गरिएका विधिहरु देहायबमोजिम रहेका छन्।"},{"type":"h3","content":"३.१. स्थलगत अवलोकन तथा निरीक्षण विधि :"},{"type":"p","content":"आयोगका अध्यक्ष र सदस्यहरुको नेतृत्वमा भाद्र २३ र २४ गते भएको प्रर्दशनको क्रममा धेरै क्षति भएका काठमाडौं उपत्यका लगायत जिल्लाहरुको प्रत्क्षय अवलोकन र निरीक्षण गरी घटनाको कारणहरु साथै क्षतिको अवस्था र विवरण संकलन गरिएको थियो। अवलोकनको लागि आयोगका अध्यक्ष र सदस्य सहितको टोली मकवानपुर, बारा, पर्सा, सुर्खेत, कैलाली, कञ्चनपुर, कास्की, चितवन, रुपन्देही, बाँके, झापा, मोरङ र सुनसरी लगायतका जिल्लाहरुमा पुगेको थियो। अवलोकनका क्रममा स्थानीय व्यक्तिहरुसँग समेत सोधपुछ गरिएको थियो। अनुसन्धान र जाँचबुझको लागि प्राथमिक तथ्याङ्ग संकलनको महत्वपूर्ण विधिको रुपमा अवलोकन निरीक्षण विधि अवलम्बन गरिएको छ।"},{"type":"h3","content":"३.२. प्रश्नोत्तर विधि (बयान, सोधपुछ तथा घटना विवरण कागज):"},{"type":"p","content":"तथ्याङ्ग संकलनमा प्रयोग भएको अर्को विधि पश्चोत्तत विधि हो। यस विधिको प्रयोग गरी आन्दोलनको क्रममा मृत्यु भएका मृतक परिवारको तर्फबाट तोकिएको ढाँचामा निश्चित प्रश्नहरु समावेश गरी घटना विवरण कागज गरिएको थियो। यसैगरी घाइतेहरुलाई समेत लिखित रुपमा घटनाको सम्बन्धमा आवश्यक र वस्तुनिष्ठ जानकारी र सूचना प्राप्त हुने गरी semi structural questions सोधिएको थियो। विभिन्न निकायको जिम्मेवारीमा रहेका व्यक्तिहरुलाई आयोगको कार्यालयमा नै उपस्थित गराई आयोगका पदाधिकारीहरुको रोहवरमा जिम्मेवारी बमोजिमका Full structure questions, semi structural questions समावेश गरी तथ्याङ्ग संकलन गरिएको थियो। यसरी पञश्चोत्तर गर्दा सही र तथ्यपरक सूचनाको प्राप्तिको लागि थप cross questions साथै पकश्चहरुमा उब्जिएका समस्याको विषयमा Follow up questions  हरु समेत समावेश गरिएको हो। घटना धेरै स्थानहरुमा भएको साथै सम्पूर्ण व्यक्तिहरुलाई प्रश्नोत्तर गर्न सम्भव नहुने हुँदा माथि उल्लेख भए बमोजिम Responsible person list तयार गरी Sampling Method बाट व्यक्ति छनोट गरिएको थियो भने बयानका आधारमा कुनै अर्को व्यक्तिलाई सोधपू्छ गर्नुपर्ने देखिएकोमा Snowball Sampling Method को आधारमा प्रश्नोत्तर गरिएको थियो ।"},{"type":"h3","content":"३.३. छलफल विधि (सरोकारवाला तथा विज्ञहरुसँगको छलफल) :"},{"type":"list","list-type":"number","content":[{"no":"लक्षित समूह छलफलः","content":"आयोगका पदाधिकारीहरुको नेतृत्वमा विभिन्न स्थानहरुका सरोकारवाला र लक्षित वर्गहरुसँग घटनाको सम्बन्धमा अन्तरक्रिया र छलफल गरी तथ्याङ्क संकलन गरिएको थियो।"},{"no":"विज्ञसँग छलफल:","content":"आयोगको कार्यलाई थप प्रभावकारी बनाउन विभिन्न विषयका विज्ञ जस्तै; सुरक्षा क्षेत्रका, सार्वजनिक प्रशासनतर्फका, कानूनका विद्धान, अधिवक्ता साथै सञ्चार जगत र अन्य विधाका विशेषज्ञहरुसँग छुलफल गरी घटनाको दौरान भएका तथ्याङ्क तथा घटना सम्बन्धमा राय समेत लिइएको थियो।"}]}]